GenRS/__init__.py
GenRS/Alg/__init__.py
GenRS/Alg/alg.py
GenRS/Alg/CFGAN/__init__.py
GenRS/Alg/CFGAN/cfgan.py
GenRS/Alg/DAE/__init__.py
GenRS/Alg/DAE/dae.py
GenRS/Alg/EASE/__init__.py
GenRS/Alg/EASE/ease.py
GenRS/Alg/IRGAN/__init__.py
GenRS/Alg/IRGAN/irgan.py
GenRS/Alg/VAE/__init__.py
GenRS/Alg/VAE/vae.py
GenRS/Cfg/__init__.py
GenRS/Cfg/cfg.py
GenRS/Data/__init__.py
GenRS/Data/data_manager.py
GenRS/Eval/__init__.py
GenRS/Eval/metrics.py
GenRS/Main/__init__.py
GenRS/Main/main.py
GenRS/Main/rec_sys.py
GenRS-0.0.5.dist-info/LICENSE
GenRS-0.0.5.dist-info/METADATA
GenRS-0.0.5.dist-info/WHEEL
GenRS-0.0.5.dist-info/top_level.txt
GenRS-0.0.5.dist-info/RECORD
