Metadata-Version: 2.1
Name: GenRS
Version: 0.0.5
Summary: A Generative learning-based Framework for Recommendation System algorithms
Home-page: https://github.com/cedo1995/GenRS
Author: Roberto Cedolin
Author-email: roberto.cedo@gmail.com
License: LICENSE
Platform: UNKNOWN
